{
  "transferencias": [
    {
      "id": "1",
      "valor": 35,
      "destino": "1212-1",
      "data": "2020-11-04T16:30:10.710Z"
    },
    {
      "id": "2",
      "valor": 40,
      "destino": "1213-1",
      "data": "2020-11-04T21:24:10.710Z"
    },
    {
      "id": "3",
      "valor": 12.5,
      "destino": "1214-1",
      "data": "2020-11-05T21:14:10.710Z"
    },
    {
      "valor": 100,
      "destino": "1234-1",
      "data": "2021-06-08T12:04:02.338Z",
      "id": "hMy5nUs"
    },
    {
      "valor": 10,
      "destino": "1010-3",
      "data": "2021-06-08T12:31:53.546Z",
      "id": "MOacQaF"
    },
    {
      "valor": 50,
      "destino": "1315-5",
      "data": "2021-06-08T12:37:53.953Z",
      "id": "70fjlBk"
    },
    {
      "valor": 123,
      "destino": "1212-1",
      "data": "2021-06-08T12:39:57.184Z",
      "id": "7p4OcHy"
    },
    {
      "valor": 200,
      "destino": "1214-3",
      "data": "2021-06-08T12:43:22.960Z",
      "id": "Einu-Bd"
    }
  ]
}